LICENSE.txt
MANIFEST.in
README.rst
requirements.txt
setup.cfg
setup.py
doc/Makefile
doc/conf.py
doc/index.rst
doc/objects.inv
doc/rst/install.rst
doc/rst/tutor.rst
doc/rst/install/libraries.rst
doc/rst/install/lib/numeric.rst
doc/rst/tutor/libraries.rst
doc/rst/tutor/lib/numeric/numeric.rst
doc/rst/tutor/lib/numeric/tut1_numpy.rst
doc/rst/tutor/lib/numeric/tut2_matplotlib.rst
doc/rst/tutor/lib/numeric/tut3_scipy.rst
doc/rst/tutor/lib/numeric/tut4_sympy.rst
doc/rst/tutor/lib/numeric/fig/matplotlib_01_basic_graph.png
doc/rst/tutor/lib/numeric/fig/matplotlib_02_labels.png
doc/rst/tutor/lib/numeric/fig/matplotlib_03_mult_plot.png
doc/rst/tutor/lib/numeric/fig/matplotlib_04_subplot.png
doc/rst/tutor/lib/numeric/fig/matplotlib_05_stem_bar.png
doc/rst/tutor/lib/numeric/fig/matplotlib_06_scatter.png
doc/rst/tutor/lib/numeric/fig/matplotlib_07_hist_boxplot.png
doc/rst/tutor/lib/numeric/fig/matplotlib_08_pie.png
doc/rst/tutor/lib/numeric/fig/matplotlib_09_polar.png
doc/rst/tutor/lib/numeric/fig/matplotlib_10_contour.png
doc/rst/tutor/lib/numeric/fig/matplotlib_11_surface.png
doc/rst/tutor/lib/numeric/fig/matplotlib_12_wireframe.png
doc/rst/tutor/lib/numeric/fig/scipy_01_interpolation.png
doc/rst/tutor/lib/numeric/fig/scipy_02_fft.png
doc/rst/tutor/lib/numeric/fig/scipy_03_filter.png
doc/rst/tutor/lib/numeric/fig/scipy_04_normal_dist.png
src/hydratk/__init__.py
src/hydratk/lib/__init__.py
src/hydratk/lib/numeric/__init__.py
src/hydratk/lib/numeric/dependencies.py
src/hydratk_lib_numeric.egg-info/PKG-INFO
src/hydratk_lib_numeric.egg-info/SOURCES.txt
src/hydratk_lib_numeric.egg-info/dependency_links.txt
src/hydratk_lib_numeric.egg-info/not-zip-safe
src/hydratk_lib_numeric.egg-info/top_level.txt
tests/travis.yoda
tests/yoda-tests/hydratk/lib/numeric/01_dummy.jedi
tests/yodahelpers/hydratk/lib/numeric/__init__.py
tests/yodalib/hydratk/lib/numeric/__init__.py